{
  "total_count": 4,
  "artifacts": [
    {
      "id": 54556559,
      "node_id": "MDg6QXJ0aWZhY3Q1NDU1NjU1OQ==",
      "name": "android-sdk-platform-tools",
      "size_in_bytes": 8709867,
      "url": "https://api.github.com/repos/petronny/action-runner-x86_64/actions/artifacts/54556559",
      "archive_download_url": "https://api.github.com/repos/petronny/action-runner-x86_64/actions/artifacts/54556559/zip",
      "expired": false,
      "created_at": "2021-04-17T16:16:51Z",
      "updated_at": "2021-04-17T16:16:52Z",
      "expires_at": "2021-07-16T16:16:30Z"
    },
    {
      "id": 54556560,
      "node_id": "MDg6QXJ0aWZhY3Q1NDU1NjU2MA==",
      "name": "android-sdk-platform-tools.23665b1d-1826-4104-be2e-97f85ec0bce9",
      "size_in_bytes": 10,
      "url": "https://api.github.com/repos/petronny/action-runner-x86_64/actions/artifacts/54556560",
      "archive_download_url": "https://api.github.com/repos/petronny/action-runner-x86_64/actions/artifacts/54556560/zip",
      "expired": false,
      "created_at": "2021-04-17T16:16:51Z",
      "updated_at": "2021-04-17T16:16:52Z",
      "expires_at": "2021-07-16T16:16:29Z"
    },
    {
      "id": 54556561,
      "node_id": "MDg6QXJ0aWZhY3Q1NDU1NjU2MQ==",
      "name": "android-sdk-platform-tools.log",
      "size_in_bytes": 42838,
      "url": "https://api.github.com/repos/petronny/action-runner-x86_64/actions/artifacts/54556561",
      "archive_download_url": "https://api.github.com/repos/petronny/action-runner-x86_64/actions/artifacts/54556561/zip",
      "expired": false,
      "created_at": "2021-04-17T16:16:51Z",
      "updated_at": "2021-04-17T16:16:52Z",
      "expires_at": "2021-07-16T16:16:32Z"
    },
    {
      "id": 54556562,
      "node_id": "MDg6QXJ0aWZhY3Q1NDU1NjU2Mg==",
      "name": "android-sdk-platform-tools.patch",
      "size_in_bytes": 1157,
      "url": "https://api.github.com/repos/petronny/action-runner-x86_64/actions/artifacts/54556562",
      "archive_download_url": "https://api.github.com/repos/petronny/action-runner-x86_64/actions/artifacts/54556562/zip",
      "expired": false,
      "created_at": "2021-04-17T16:16:51Z",
      "updated_at": "2021-04-17T16:16:52Z",
      "expires_at": "2021-07-16T16:16:31Z"
    }
  ]
}
