{
  "total_count": 4,
  "artifacts": [
    {
      "id": 63568966,
      "node_id": "MDg6QXJ0aWZhY3Q2MzU2ODk2Ng==",
      "name": "kiwiirc",
      "size_in_bytes": 1837961,
      "url": "https://api.github.com/repos/petronny/action-runner-x86_64/actions/artifacts/63568966",
      "archive_download_url": "https://api.github.com/repos/petronny/action-runner-x86_64/actions/artifacts/63568966/zip",
      "expired": false,
      "created_at": "2021-05-27T16:18:07Z",
      "updated_at": "2021-05-27T16:18:08Z",
      "expires_at": "2021-08-25T16:17:25Z"
    },
    {
      "id": 63568967,
      "node_id": "MDg6QXJ0aWZhY3Q2MzU2ODk2Nw==",
      "name": "kiwiirc.c982639a-ee8d-49c4-b8d2-db14bd629643",
      "size_in_bytes": 10,
      "url": "https://api.github.com/repos/petronny/action-runner-x86_64/actions/artifacts/63568967",
      "archive_download_url": "https://api.github.com/repos/petronny/action-runner-x86_64/actions/artifacts/63568967/zip",
      "expired": false,
      "created_at": "2021-05-27T16:18:07Z",
      "updated_at": "2021-05-27T16:18:08Z",
      "expires_at": "2021-08-25T16:17:24Z"
    },
    {
      "id": 63568968,
      "node_id": "MDg6QXJ0aWZhY3Q2MzU2ODk2OA==",
      "name": "kiwiirc.log",
      "size_in_bytes": 16823,
      "url": "https://api.github.com/repos/petronny/action-runner-x86_64/actions/artifacts/63568968",
      "archive_download_url": "https://api.github.com/repos/petronny/action-runner-x86_64/actions/artifacts/63568968/zip",
      "expired": false,
      "created_at": "2021-05-27T16:18:07Z",
      "updated_at": "2021-05-27T16:18:08Z",
      "expires_at": "2021-08-25T16:17:26Z"
    },
    {
      "id": 63568969,
      "node_id": "MDg6QXJ0aWZhY3Q2MzU2ODk2OQ==",
      "name": "kiwiirc.patch",
      "size_in_bytes": 731,
      "url": "https://api.github.com/repos/petronny/action-runner-x86_64/actions/artifacts/63568969",
      "archive_download_url": "https://api.github.com/repos/petronny/action-runner-x86_64/actions/artifacts/63568969/zip",
      "expired": false,
      "created_at": "2021-05-27T16:18:07Z",
      "updated_at": "2021-05-27T16:18:08Z",
      "expires_at": "2021-08-25T16:17:25Z"
    }
  ]
}
